imageconv.py
imageconv/__init__.py
imageconv/__main__.py
imageconv/imageconv.py
imageconv-1.4.dist-info/METADATA
imageconv-1.4.dist-info/WHEEL
imageconv-1.4.dist-info/entry_points.txt
imageconv-1.4.dist-info/top_level.txt
imageconv-1.4.dist-info/RECORD
